taal
