Metadata-Version: 1.0
Name: taal
Version: 0.4.2
Summary: Model translations
Home-page: https://github.com/onefinestay/taal
Author: onefinestay
Author-email: engineering@onefinestay.com
License: UNKNOWN
Platform: UNKNOWN
Classifier: Development Status :: 3 - Alpha
Classifier: Programming Language :: Python
Classifier: Intended Audience :: Developers
Classifier: Natural Language :: English
Classifier: Topic :: Software Development
Classifier: Topic :: Utilities
